helper/__init__.py
helper/config.py
helper/db_connector.py
helper/kpi.py
helper/logger.py
helper/reports_utils.py
tests/__init__.py
automation_helper-0.0.10.dist-info/METADATA
automation_helper-0.0.10.dist-info/WHEEL
automation_helper-0.0.10.dist-info/top_level.txt
automation_helper-0.0.10.dist-info/RECORD
