Metadata-Version: 2.1
Name: automation-helper
Version: 0.0.10
Summary: automation helper library
Author: juan matias tulli
Author-email: jmatiastulli@gmail.com
License: jmt
Classifier: Intended Audience :: Developers
Classifier: Programming Language :: Python
Classifier: Programming Language :: Python :: 3.8
Classifier: Programming Language :: Python :: 3.9
Classifier: Operating System :: OS Independent
Requires-Dist: pandas
Requires-Dist: psycopg2
Requires-Dist: datetime
Requires-Dist: configparser
